stripe_testing/__init__.py
stripe_testing-0.1.0.dist-info/DESCRIPTION.rst
stripe_testing-0.1.0.dist-info/METADATA
stripe_testing-0.1.0.dist-info/RECORD
stripe_testing-0.1.0.dist-info/WHEEL
stripe_testing-0.1.0.dist-info/metadata.json
stripe_testing-0.1.0.dist-info/top_level.txt
