Metadata-Version: 2.0
Name: stripe-testing
Version: 0.1.0
Summary: Bits and bobs for testing with Stripe
Home-page: https://github.com/bennylope/stripe_testing
Author: Ben Lopatin
Author-email: ben@benlopatin.com
License: MIT license
Keywords: stripe_testing
Platform: UNKNOWN
Classifier: Development Status :: 2 - Pre-Alpha
Classifier: Intended Audience :: Developers
Classifier: License :: OSI Approved :: MIT License
Classifier: Natural Language :: English
Classifier: Programming Language :: Python :: 2
Classifier: Programming Language :: Python :: 2.7
Classifier: Programming Language :: Python :: 3
Classifier: Programming Language :: Python :: 3.4
Classifier: Programming Language :: Python :: 3.5
Classifier: Programming Language :: Python :: 3.6
